pylint_wrapper.cpython-38-x86_64-linux-gnu.so
atosdevopstools_cli.cpython-38-x86_64-linux-gnu.so
gitlab_wrapper.cpython-38-x86_64-linux-gnu.so
pypi_wrapper.cpython-38-x86_64-linux-gnu.so
tests/test_functional/test_scripts.py
tests/test_functional/__init__.py
tests/test_end_to_end/__init__.py
tests/test_unit/test_scripts.py
tests/test_unit/__init__.py
atosdevopstools-1.1.2.dist-info/WHEEL
atosdevopstools-1.1.2.dist-info/METADATA
atosdevopstools-1.1.2.dist-info/entry_points.txt
atosdevopstools-1.1.2.dist-info/top_level.txt
atosdevopstools-1.1.2.dist-info/RECORD
atosdevopstools-1.1.2.dist-info/LICENSE
