Metadata-Version: 2.1
Name: atosdevopstools
Version: 1.1.2
Summary: DevOps utils
Home-page: https://scm.atosresearch.eu/ari/smartnet/pylib/atos-devops-tools
Author: 2020, ATOS Research and Innovation
Author-email: smartnet@atosresearh.eu
Maintainer: Guillermo Gomez
License: OSI Approved :: Apache Software License
Platform: UNKNOWN
Requires-Python: ~=3.8
Requires-Dist: click (~=7.1.2)
Requires-Dist: requests (~=2.25.0)
Requires-Dist: anybadge (~=1.7.0)
Requires-Dist: pytest (~=6.2.1)
Requires-Dist: pytest-cov (~=2.8.1)
Requires-Dist: pylint (~=2.6.0)
